ManualPytestPlugin/__init__.py
ManualPytestPlugin/conftest.py
ManualPytestPlugin/testcases/__init__.py
ManualPytestPlugin/testcases/test_demo01.py
ManualPytestPlugin/testcases/test_demo02.py
pytest_xiuyu-1.0.0.dist-info/METADATA
pytest_xiuyu-1.0.0.dist-info/WHEEL
pytest_xiuyu-1.0.0.dist-info/entry_points.txt
pytest_xiuyu-1.0.0.dist-info/top_level.txt
pytest_xiuyu-1.0.0.dist-info/RECORD
