Metadata-Version: 2.1
Name: pytest-xiuyu
Version: 1.0.0
Summary: This is a pytest plugin
Home-page: https://github.com/TonyGao2527/pytest-xiuyu
Author: TonyGao
Author-email: 5942527@qq.com
Classifier: Development Status :: 5 - Production/Stable
